stockstir/__init__.py
stockstir/api.py
stockstir/cli.py
stockstir/gather_info.py
stockstir/providers.py
stockstir/tools.py
stockstir-2.1.7.dist-info/METADATA
stockstir-2.1.7.dist-info/WHEEL
stockstir-2.1.7.dist-info/entry_points.txt
stockstir-2.1.7.dist-info/licenses/LICENSE
stockstir-2.1.7.dist-info/RECORD
