Metadata-Version: 2.4
Name: Stockstir
Version: 2.1.7
Summary: Easily gather stock data of any company in any of your Python projects
Project-URL: Homepage, https://github.com/PatzEdi
Project-URL: Repository, https://github.com/PatzEdi/Stockstir
Project-URL: Bug Tracker, https://github.com/PatzEdi/Stockstir/issues
Author-email: PatzEdi <patzedigithub@gmail.com>
License-File: LICENSE
Keywords: stockdata,stockmanagement,stockmarkettool,stocks
Classifier: License :: OSI Approved :: MIT License
Classifier: Operating System :: OS Independent
Classifier: Programming Language :: Python :: 3
Requires-Python: >=3.9
Requires-Dist: requests
